{
  "race_date": "2026-07-12",
  "race_number": 3,
  "timestamp_source": "2026-07-12_13-40-09",
  "strategy": "1B3L_ctrl_Multi Contender Dominant Favorite",
  "strategy_version": "v1.0_ctrl",
  "scenario": "Multi Contender Dominant Favorite",
  "tier": "Multi Contender Dominant Favorite",
  "favourite_odds": 4.0,
  "n_contenders": 3,
  "BANKER": 6,
  "BANKER_source": "Q_prediction_rank==1",
  "BANKER_odds": 5.3,
  "BANKER_total_score": 111.92,
  "LEG1": 10,
  "LEG1_source": "lowest_current_win",
  "LEG2": 13,
  "LEG2_source": "second_lowest_current_win",
  "LEG3": 14,
  "LEG3_source": "third_lowest_current_win",
  "LEG4": 8,
  "LEG4_source": "20-99 odds",
  "LEG5": null,
  "LEG5_source": "None",
  "race_class": 4,
  "race_distance": 1400,
  "race_course": "沙田",
  "decision_log": [
    "Scenario: ST Multi Contender Dominant Favorite (field: 14 runners) ",
    "Odds < 6: [H10]@4.0  [H13]@5.0  [H6]@5.3",
    "Odds 6–10: [H14]@6.9  [H2]@8.5  [H9]@8.8",
    "Odds 11–20: (none)",
    "Odds > 20: [H8]@27.0  [H12]@28.0  [H3]@37.0  [H5]@40.0  [H7]@40.0  [H4]@48.0  [H11]@71.0  [H1]@72.0",
    "Predicted Odds Pattern: Q_prediction_rank==1 > lowest_current_win > second_lowest_current_win > third_lowest_current_win > 20-99 odds",
    "Banker selected: H6 via Q_prediction_rank==1",
    "Legs selected: H10 via lowest_current_win, H13 via second_lowest_current_win, H14 via third_lowest_current_win, H8 via 20-99 odds"
  ]
}