{
  "race_date": "2026-03-15",
  "race_number": 2,
  "timestamp_source": "2026-03-15_10-15-57",
  "strategy": "1B3L_Diamond",
  "strategy_version": "v2.2_1B3L",
  "tier": "Diamond",
  "expected_success_rate": "38-41%",
  "BANKER": 8,
  "BANKER_source": "PredV2_Diamond(gap=18.1)",
  "banker_swapped": false,
  "banker_agreement": 0,
  "banker_pace_score": 45,
  "LEG1": null,
  "LEG1_source": "None",
  "LEG2": 9,
  "LEG2_source": "RTG2",
  "LEG3": 7,
  "LEG3_source": "Q3",
  "LEG4": 11,
  "LEG4_source": "QPLeg1(odds=10.0)",
  "race_class": 5,
  "race_distance": 1200,
  "race_course": "沙田",
  "ml_gap": 18.12,
  "decision_log": [
    "Top-1 picks — Q1:9  QP1:9  SS1:None  RTG1:7",
    "ML prediction gap: 18.12",
    "✓ DIAMOND tier (gap=18.12): banker = 8",
    "Pace suitability: 45.0",
    "Second-slot picks — Q2:8  QP2:8  SS2:None  RTG2:9  Q3:7  QP3:5  LNG2:5",
    "⚠ LEG1: no valid pick available",
    "LEG1: None from None",
    "RTG3 (fetched early for fallback): 5",
    "LEG2: 9 from RTG2",
    "  Q4:5  QPLeg1:11",
    "⚠ LEG3 candidate QP2=8 duplicates banker/LEG1/LEG2, trying next",
    "LEG3: 7 from Q3",
    "LEG4(alt): 11 from QPLeg1(odds=10.0) — QPLeg1 qualifies (odds ≤12)"
  ]
}