{
  "race_date": "2026-04-19",
  "race_number": 8,
  "timestamp_source": "2026-04-19_10-16-27",
  "strategy": "1B3L_ctrl_Multi Contender Dominant Favorite",
  "strategy_version": "v1.0_ctrl",
  "scenario": "Multi Contender Dominant Favorite",
  "tier": "Multi Contender Dominant Favorite",
  "favourite_odds": 2.9,
  "n_contenders": 3,
  "BANKER": 3,
  "BANKER_source": "Q_prediction_rank==1",
  "BANKER_odds": 4.4,
  "BANKER_total_score": 149.56,
  "LEG1": 6,
  "LEG1_source": "lowest_current_win",
  "LEG2": 1,
  "LEG2_source": "second_lowest_current_win",
  "LEG3": 11,
  "LEG3_source": "third_lowest_current_win",
  "LEG4": 4,
  "LEG4_source": "20-99 odds",
  "LEG5": null,
  "LEG5_source": "None",
  "race_class": 3,
  "race_distance": 1200,
  "race_course": "沙田",
  "decision_log": [
    "Scenario: ST Multi Contender Dominant Favorite (field: 10 runners) ",
    "Odds < 6: [H6]@2.9  [H3]@4.4  [H1]@5.8",
    "Odds 6–10: [H11]@6.1",
    "Odds 11–20: [H7]@11.0  [H2]@17.0  [H4]@20.0",
    "Odds > 20: [H8]@22.0  [H9]@23.0  [H10]@34.0",
    "Predicted Odds Pattern: Q_prediction_rank==1 > lowest_current_win > second_lowest_current_win > third_lowest_current_win > 20-99 odds",
    "Banker selected: H3 via Q_prediction_rank==1",
    "Legs selected: H6 via lowest_current_win, H1 via second_lowest_current_win, H11 via third_lowest_current_win, H4 via 20-99 odds"
  ]
}