{
  "race_date": "2026-07-04",
  "race_number": 4,
  "timestamp_source": "2026-07-04_13-38-36",
  "strategy": "1B3L_Gold-Multi Contender Dominant Favorite",
  "strategy_version": "v6.0_merged",
  "scenario": "Multi Contender Dominant Favorite",
  "tier": "Gold",
  "expected_success_rate": "45%",
  "favourite_odds": 2.5,
  "n_contenders": 3,
  "banker_odds_cap": 8.0,
  "BANKER": 4,
  "BANKER_source": "consensus_agreement(3)",
  "BANKER_odds": 2.5,
  "BANKER_total_score": 170.21,
  "DUAL_BANKER": 5,
  "DUAL_BANKER_source": "consensus_backup(Q2/QP2/SS2)",
  "DUAL_BANKER_odds": 3.0,
  "DUAL_BANKER_total_score": 172.25,
  "LEG1": 5,
  "LEG1_source": "consensus_backup(Q2/QP2/SS2)",
  "LEG2": 3,
  "LEG2_source": "RTG3",
  "LEG3": 1,
  "LEG3_source": "<10 odds (contender target)",
  "LEG4": 2,
  "LEG4_source": "15-99 odds (VC fallback)",
  "LEG5": null,
  "LEG5_source": "None",
  "race_class": 2,
  "race_distance": 1200,
  "race_course": "沙田",
  "decision_log": [
    "Scenario: ST Multi Contender Dominant Favorite (field: 7 runners)",
    "Odds < 6: [H4]@2.5  [H5]@3.0  [H3]@5.8",
    "Odds 6-10: [H1]@6.8",
    "Odds 11-20: [H6]@16.0  [H7]@16.0",
    "Odds > 20: [H2]@24.0",
    "[CHECKLIST PRIMARY] Banker signal: H5 (odds=3.0) — 60% top-3 rate",
    "[CHECKLIST PRIMARY] No place signal this race (null).",
    "Tier assigned (v6.0): Gold (banker_source=consensus_agreement(3), banker_odds=2.5, class=2)",
    "LEG2: RTG3 H3 accepted (ML rank=3 ≤ 7). [RULE-1]",
    "LEG5: No Value Contender — fell back to 15-99 odds. [RULE-2]",
    "Predicted Odds Pattern: consensus_agreement(3) > consensus_backup(Q2/QP2/SS2) > RTG3 > <10 odds (contender target) > 15-99 odds (VC fallback)",
    "Banker selected: H4 via consensus_agreement(3)",
    "Dual Banker (REC-3): H5 via consensus_backup(Q2/QP2/SS2)",
    "Legs selected: H5 via consensus_backup(Q2/QP2/SS2), H3 via RTG3, H1 via <10 odds (contender target), H2 via 15-99 odds (VC fallback)"
  ]
}