{
  "race_date": "2026-02-22",
  "race_number": 1,
  "timestamp_source": "2026-02-21_21-08-27",
  "strategy": "4BOX",
  "strategy_version": "v1.0_unified",
  "tier": "Toxic-Unsafe",
  "expected_success_rate": "41.18%",
  "BANKER": 1,
  "BANKER_source": "Q_Fallback_Toxic-Unsafe(Class4-1000m)",
  "banker_swapped": false,
  "banker_pace_score": 45,
  "LEG1": 6,
  "LEG1_source": "PredV2_Rank1",
  "LEG2": 4,
  "LEG2_source": "PredV2_Rank2",
  "LEG3": 11,
  "LEG3_source": "PredV2_Rank3",
  "LEG4": 13,
  "LEG4_source": "QPLeg1",
  "LEG5": null,
  "LEG5_source": null,
  "race_class": 4,
  "race_distance": 1000,
  "race_course": "沙田",
  "ml_gap": 2.27,
  "decision_log": [
    "⚠ QP banker is None, using Q as fallback",
    "Initial banker: 1 (from Q_Fallback)",
    "ML prediction gap: 2.27",
    "⚠ TOXIC tier: Unsafe conditions (Class4-1000m)",
    "Pace suitability score: 45.0",
    "⚠ Low pace suitability (<75), tier marked as Unsafe",
    "LEG1: 6 from PredV2_Rank1",
    "LEG2: 4 from PredV2_Rank2",
    "LEG3: 11 from PredV2_Rank3",
    "LEG4: 13 from QPLeg1 (alternate)"
  ]
}