{
    "meta": {
        "date": "2026-04-01",
        "race_number": 6,
        "course": "沙田",
        "distance": 1200,
        "class": "第四班"
    },
    "ranking": {
        "score1": 8,
        "horse_name1": "祥勝力駒",
        "draw1": "7",
        "score_value1": 34.27,
        "factors1": {
            "weight": 125.0,
            "days_away": 24,
            "fast_works": 3
        },
        "score2": 9,
        "horse_name2": "起舞奜奜",
        "draw2": "12",
        "score_value2": 33.52,
        "factors2": {
            "weight": 124.0,
            "days_away": 24,
            "fast_works": 4
        },
        "score3": 3,
        "horse_name3": "顯勝高昇",
        "draw3": "2",
        "score_value3": 22.18,
        "factors3": {
            "weight": 133.0,
            "days_away": 24,
            "fast_works": 5
        }
    }
}