{
  "race_date": "2026-05-13",
  "race_number": 8,
  "timestamp_source": "2026-05-13_17-26-29",
  "strategy": "1B3L_ctrl_Multi Contender No Dominant Favorite",
  "strategy_version": "v1.0_ctrl",
  "scenario": "Multi Contender No Dominant Favorite",
  "tier": "Multi Contender No Dominant Favorite",
  "favourite_odds": 4.3,
  "n_contenders": 3,
  "BANKER": 2,
  "BANKER_source": "Contender=='YES' lowest current_win",
  "BANKER_odds": 4.3,
  "BANKER_total_score": 129.14,
  "LEG1": 10,
  "LEG1_source": "Q_prediction_rank==2",
  "LEG2": 11,
  "LEG2_source": "Q_prediction_rank==3",
  "LEG3": 8,
  "LEG3_source": "20-99 odds",
  "LEG4": null,
  "LEG4_source": "None",
  "LEG5": null,
  "LEG5_source": "None",
  "race_class": 3,
  "race_distance": 1200,
  "race_course": "跑馬地",
  "decision_log": [
    "Scenario: HV Multi Contender No Dominant Favorite (field: 12 runners) ",
    "Odds < 6: [H2]@4.3  [H10]@4.3  [H1]@5.5",
    "Odds 6–10: [H9]@10.0",
    "Odds 11–20: [H5]@12.0  [H6]@12.0  [H11]@12.0  [H7]@15.0  [H4]@17.0",
    "Odds > 20: [H8]@26.0  [H3]@30.0  [H12]@31.0",
    "Predicted Odds Pattern: Contender=='YES' lowest current_win > Q_prediction_rank==2 > Q_prediction_rank==3 > 20-99 odds > None",
    "Banker selected: H2 via Contender=='YES' lowest current_win",
    "Legs selected: H10 via Q_prediction_rank==2, H11 via Q_prediction_rank==3, H8 via 20-99 odds"
  ]
}