{
  "race_date": "2026-06-13",
  "race_number": 9,
  "timestamp_source": "2026-06-13_13-43-53",
  "strategy": "1B3L_Silver-Two Contender No Dominant Favorite",
  "strategy_version": "v6.0_merged",
  "scenario": "Two Contender No Dominant Favorite",
  "tier": "Silver",
  "expected_success_rate": "37%",
  "favourite_odds": 4.9,
  "n_contenders": 2,
  "banker_odds_cap": 8.0,
  "BANKER": 1,
  "BANKER_source": "scenC_consensus(2)_capped",
  "BANKER_odds": 4.9,
  "BANKER_total_score": 154.63,
  "DUAL_BANKER": 2,
  "DUAL_BANKER_source": "consensus_backup(Q2/QP2/SS2)",
  "DUAL_BANKER_odds": 5.7,
  "DUAL_BANKER_total_score": 161.22,
  "LEG1": 2,
  "LEG1_source": "consensus_backup(Q2/QP2/SS2)",
  "LEG2": 6,
  "LEG2_source": "RTG3",
  "LEG3": 5,
  "LEG3_source": "20-99 odds (longshot squeeze)",
  "LEG4": 3,
  "LEG4_source": "6-15 odds",
  "LEG5": 4,
  "LEG5_source": "value_contender(6.0-14.0,ML_rank=5)",
  "race_class": 3,
  "race_distance": 1200,
  "race_course": "沙田",
  "decision_log": [
    "Scenario: ST Two Contender No Dominant Favorite (field: 12 runners)",
    "Odds < 6: [H1]@4.9  [H2]@5.7",
    "Odds 6-10: [H3]@6.6  [H10]@7.1  [H4]@9.2  [H11]@10.0",
    "Odds 11-20: [H7]@11.0  [H6]@16.0  [H8]@17.0  [H9]@17.0",
    "Odds > 20: [H5]@26.0  [H12]@26.0",
    "[CHECKLIST PRIMARY] No banker signal this race (null).",
    "[CHECKLIST PRIMARY] Place signal: H3 (odds=6.6) — 60% top-3 rate",
    "Scenario C: 2 predictors agree on H1 (odds 4.9 ≤ 8.0). [REC-2]",
    "Tier assigned (v6.0): Silver (banker_source=scenC_consensus(2)_capped, banker_odds=4.9, class=3)",
    "LEG2: RTG3 H6 accepted (ML rank=4 ≤ 7). [RULE-1]",
    "LEG5: Value Contender H4 (odds=9.2, ML rank=5). [RULE-2]",
    "Predicted Odds Pattern: scenC_consensus(2)_capped > consensus_backup(Q2/QP2/SS2) > RTG3 > 20-99 odds (longshot squeeze) > 6-15 odds",
    "Banker selected: H1 via scenC_consensus(2)_capped",
    "Dual Banker (REC-3): H2 via consensus_backup(Q2/QP2/SS2)",
    "Legs selected: H2 via consensus_backup(Q2/QP2/SS2), H6 via RTG3, H5 via 20-99 odds (longshot squeeze), H3 via 6-15 odds, H4 via value_contender(6.0-14.0,ML_rank=5)"
  ]
}