{
  "race_date": "2026-07-08",
  "race_number": 2,
  "timestamp_source": "2026-07-08_17-32-41",
  "strategy": "1B3L_ctrl_Strong Favorite Race",
  "strategy_version": "v1.0_ctrl",
  "scenario": "Strong Favorite Race",
  "tier": "Strong Favorite Race",
  "favourite_odds": 3.4,
  "n_contenders": 1,
  "BANKER": 2,
  "BANKER_source": "favorite",
  "BANKER_odds": 3.4,
  "BANKER_total_score": 119.18,
  "LEG1": 4,
  "LEG1_source": "6-10 odds",
  "LEG2": 1,
  "LEG2_source": "6-10 odds",
  "LEG3": 6,
  "LEG3_source": "10-15 odds",
  "LEG4": 9,
  "LEG4_source": "6-15 odds",
  "LEG5": null,
  "LEG5_source": "None",
  "race_class": 4,
  "race_distance": 1650,
  "race_course": "跑馬地",
  "decision_log": [
    "Scenario: HV Strong Favorite Race (field: 12 runners) ",
    "Odds < 6: [H2]@3.4",
    "Odds 6–10: [H8]@6.2  [H1]@7.2  [H4]@7.7  [H9]@8.4  [H6]@10.0  [H10]@10.0",
    "Odds 11–20: [H5]@15.0  [H12]@18.0",
    "Odds > 20: [H7]@30.0  [H3]@79.0  [H11]@89.0",
    "Predicted Odds Pattern: favorite > 6-10 odds > 6-10 odds > 10-15 odds > 6-15 odds",
    "Banker selected: H2 via favorite",
    "Legs selected: H4 via 6-10 odds, H1 via 6-10 odds, H6 via 10-15 odds, H9 via 6-15 odds"
  ]
}