{
  "race_date": "2026-06-24",
  "race_number": 1,
  "timestamp_source": "2026-06-24_17-32-25",
  "strategy": "1B3L_ctrl_Two Contender No Dominant Favorite",
  "strategy_version": "v1.0_ctrl",
  "scenario": "Two Contender No Dominant Favorite",
  "tier": "Two Contender No Dominant Favorite",
  "favourite_odds": 4.4,
  "n_contenders": 2,
  "BANKER": 3,
  "BANKER_source": "Q_prediction_rank==1",
  "BANKER_odds": 4.7,
  "BANKER_total_score": 90.11,
  "LEG1": 2,
  "LEG1_source": "6-10 odds",
  "LEG2": 5,
  "LEG2_source": "10-15 odds",
  "LEG3": 8,
  "LEG3_source": "favorite",
  "LEG4": null,
  "LEG4_source": "None",
  "LEG5": null,
  "LEG5_source": "None",
  "race_class": 5,
  "race_distance": 2200,
  "race_course": "跑馬地",
  "decision_log": [
    "Scenario: HV Two Contender No Dominant Favorite (field: 12 runners) ",
    "Odds < 6: [H8]@4.4  [H3]@4.7",
    "Odds 6–10: [H2]@9.5  [H10]@9.6  [H6]@10.0",
    "Odds 11–20: [H1]@11.0  [H5]@11.0  [H9]@11.0  [H7]@17.0  [H11]@17.0  [H4]@18.0",
    "Odds > 20: [H12]@28.0",
    "Predicted Odds Pattern: Q_prediction_rank==1 > 6-10 odds > 10-15 odds > favorite > None",
    "Banker selected: H3 via Q_prediction_rank==1",
    "Legs selected: H2 via 6-10 odds, H5 via 10-15 odds, H8 via favorite"
  ]
}