{
  "Race Date": "2025-06-04",
  "Race Number": 1,
  "Horses": [
    {
      "horseID": "HK_2023_J452",
      "Horse Number": "1",
      "Horse Name": "步風雷",
      "Weight": "135",
      "Trainer": "伍鵬志",
      "Jockey": "黃智弘",
      "Post": "2",
      "First Win Index": "31.8",
      "Race Day Win Index": "34.8",
      "lastWin": "97",
      "lastPosition": "07"
    },
    {
      "horseID": "HK_2022_H196",
      "Horse Number": "2",
      "Horse Name": "上市魅力",
      "Weight": "132",
      "Trainer": "蘇偉賢",
      "Jockey": "艾兆禮",
      "Post": "6",
      "First Win Index": "10.6",
      "Race Day Win Index": "5.6",
      "lastWin": "11",
      "lastPosition": "05"
    },
    {
      "horseID": "HK_2020_E478",
      "Horse Number": "3",
      "Horse Name": "躡景追飛",
      "Weight": "130",
      "Trainer": "沈集成",
      "Jockey": "奧爾民",
      "Post": "11",
      "First Win Index": "99",
      "Race Day Win Index": "99",
      "lastWin": "17",
      "lastPosition": "07"
    },
    {
      "horseID": "HK_2023_J493",
      "Horse Number": "4",
      "Horse Name": "不假外求",
      "Weight": "130",
      "Trainer": "黎昭昇",
      "Jockey": "鍾易禮",
      "Post": "5",
      "First Win Index": "31.8",
      "Race Day Win Index": "73.6",
      "lastWin": "91",
      "lastPosition": "06"
    },
    {
      "horseID": "HK_2022_H357",
      "Horse Number": "5",
      "Horse Name": "碧海藍天",
      "Weight": "130",
      "Trainer": "蔡約翰",
      "Jockey": "艾道拿",
      "Post": "7",
      "First Win Index": "99",
      "Race Day Win Index": "26.4",
      "lastWin": "21",
      "lastPosition": "11"
    },
    {
      "horseID": "HK_2019_D241",
      "Horse Number": "6",
      "Horse Name": "香港精神",
      "Weight": "128",
      "Trainer": "葉楚航",
      "Jockey": "田泰安",
      "Post": "3",
      "First Win Index": "4.3",
      "Race Day Win Index": "5.0",
      "lastWin": "6.2",
      "lastPosition": "08"
    },
    {
      "horseID": "HK_2021_G301",
      "Horse Number": "7",
      "Horse Name": "豐盛多彩",
      "Weight": "127",
      "Trainer": "韋達",
      "Jockey": "蔡明紹",
      "Post": "12",
      "First Win Index": "99",
      "Race Day Win Index": "99",
      "lastWin": "30",
      "lastPosition": "10"
    },
    {
      "horseID": "HK_2023_J211",
      "Horse Number": "8",
      "Horse Name": "裕達寶駒",
      "Weight": "126",
      "Trainer": "丁冠豪",
      "Jockey": "梁家俊",
      "Post": "8",
      "First Win Index": "99",
      "Race Day Win Index": "99",
      "lastWin": "39",
      "lastPosition": "07"
    },
    {
      "horseID": "HK_2022_H386",
      "Horse Number": "9",
      "Horse Name": "同寶寶",
      "Weight": "125",
      "Trainer": "伍鵬志",
      "Jockey": "潘頓",
      "Post": "9",
      "First Win Index": "4.2",
      "Race Day Win Index": "4.4",
      "lastWin": "3.9",
      "lastPosition": "04"
    },
    {
      "horseID": "HK_2020_E448",
      "Horse Number": "10",
      "Horse Name": "皇金風速",
      "Weight": "124",
      "Trainer": "蘇偉賢",
      "Jockey": "希威森",
      "Post": "1",
      "First Win Index": "5.0",
      "Race Day Win Index": "6.7",
      "lastWin": "20",
      "lastPosition": "03"
    },
    {
      "horseID": "HK_2022_H034",
      "Horse Number": "11",
      "Horse Name": "皮具大師",
      "Weight": "123",
      "Trainer": "文家良",
      "Jockey": "巴度",
      "Post": "10",
      "First Win Index": "7.2",
      "Race Day Win Index": "7.8",
      "lastWin": "4.4",
      "lastPosition": "03"
    },
    {
      "horseID": "HK_2021_G072",
      "Horse Number": "12",
      "Horse Name": "喜悅一生",
      "Weight": "115",
      "Trainer": "鄭俊偉",
      "Jockey": "楊明綸",
      "Post": "4",
      "First Win Index": "31.8",
      "Race Day Win Index": "32.0",
      "lastWin": "18",
      "lastPosition": "08"
    }
  ]
}