{
  "Race Date": "2025-09-07",
  "Race Number": 3,
  "Horses": [
    {
      "horseID": "HK_2023_J062",
      "Horse Number": "1",
      "Horse Name": "嘉應高昇",
      "Weight": "135",
      "Trainer": "大衛希斯",
      "Jockey": "潘頓",
      "Post": "4",
      "First Win Index": "2.7",
      "Race Day Win Index": "2.6",
      "lastWin": "1",
      "lastPosition": "01"
    },
    {
      "horseID": "HK_2021_G180",
      "Horse Number": "2",
      "Horse Name": "金鑽貴人",
      "Weight": "126",
      "Trainer": "文家良",
      "Jockey": "梁家俊",
      "Post": "5",
      "First Win Index": "6.3",
      "Race Day Win Index": "7.0",
      "lastWin": "18",
      "lastPosition": "04"
    },
    {
      "horseID": "HK_2020_E356",
      "Horse Number": "3",
      "Horse Name": "幸運有您",
      "Weight": "116",
      "Trainer": "羅富全",
      "Jockey": "艾兆禮",
      "Post": "10",
      "First Win Index": "10.9",
      "Race Day Win Index": "6.6",
      "lastWin": "22",
      "lastPosition": "08"
    },
    {
      "horseID": "HK_2022_H294",
      "Horse Number": "4",
      "Horse Name": "美麗第一",
      "Weight": "115",
      "Trainer": "告東尼",
      "Jockey": "巴度",
      "Post": "3",
      "First Win Index": "5.0",
      "Race Day Win Index": "4.5",
      "lastWin": "3.9",
      "lastPosition": "01"
    },
    {
      "horseID": "HK_2021_G404",
      "Horse Number": "5",
      "Horse Name": "維港智能",
      "Weight": "115",
      "Trainer": "游達榮",
      "Jockey": "班德禮",
      "Post": "8",
      "First Win Index": "99",
      "Race Day Win Index": "99",
      "lastWin": "20",
      "lastPosition": "05"
    },
    {
      "horseID": "HK_2022_H408",
      "Horse Number": "6",
      "Horse Name": "合夥奔馳",
      "Weight": "115",
      "Trainer": "呂健威",
      "Jockey": "董明朗",
      "Post": "2",
      "First Win Index": "13.5",
      "Race Day Win Index": "25.2",
      "lastWin": "26",
      "lastPosition": "01"
    },
    {
      "horseID": "HK_2022_H368",
      "Horse Number": "7",
      "Horse Name": "精算暴雪",
      "Weight": "115",
      "Trainer": "蔡約翰",
      "Jockey": "楊明綸",
      "Post": "1",
      "First Win Index": "57.1",
      "Race Day Win Index": "66.0",
      "lastWin": "4.8",
      "lastPosition": "07"
    },
    {
      "horseID": "HK_2023_J333",
      "Horse Number": "8",
      "Horse Name": "魔術控制",
      "Weight": "115",
      "Trainer": "巫偉傑",
      "Jockey": "蔡明紹",
      "Post": "9",
      "First Win Index": "99",
      "Race Day Win Index": "99",
      "lastWin": "12",
      "lastPosition": "05"
    },
    {
      "horseID": "HK_2023_J316",
      "Horse Number": "9",
      "Horse Name": "天天同樂",
      "Weight": "115",
      "Trainer": "羅富全",
      "Jockey": "潘明輝",
      "Post": "7",
      "First Win Index": "13.1",
      "Race Day Win Index": "21.9",
      "lastWin": "4.7",
      "lastPosition": "04"
    },
    {
      "horseID": "HK_2023_J142",
      "Horse Number": "10",
      "Horse Name": "開心寶寶",
      "Weight": "115",
      "Trainer": "呂健威",
      "Jockey": "鍾易禮",
      "Post": "6",
      "First Win Index": "99",
      "Race Day Win Index": "99",
      "lastWin": "6.9",
      "lastPosition": "10"
    },
    {
      "horseID": "HK_2023_J008",
      "Horse Number": "11",
      "Horse Name": "華麗再勝",
      "Weight": "115",
      "Trainer": "沈集成",
      "Jockey": "黃寶妮",
      "Post": "11",
      "First Win Index": "99",
      "Race Day Win Index": "99",
      "lastWin": "20",
      "lastPosition": "10"
    },
    {
      "horseID": "HK_2020_E061",
      "Horse Number": "12",
      "Horse Name": "人和家興",
      "Weight": "115",
      "Trainer": "大衛希斯",
      "Jockey": "田泰安",
      "Post": "12",
      "First Win Index": "74.2",
      "Race Day Win Index": "99",
      "lastWin": "6.9",
      "lastPosition": "02"
    }
  ]
}