{
  "Race Date": "2026-05-06",
  "Race Number": 1,
  "Horses": [
    {
      "horseID": "HK_2023_J508",
      "Horse Number": "1",
      "Horse Name": "光輝歲月",
      "Weight": "135",
      "Trainer": "游達榮",
      "Jockey": "霍宏聲",
      "Post": "7",
      "First Win Index": "3.6",
      "Race Day Win Index": "4.4",
      "lastWin": "21",
      "lastPosition": "04"
    },
    {
      "horseID": "HK_2023_J213",
      "Horse Number": "2",
      "Horse Name": "君智盛",
      "Weight": "134",
      "Trainer": "姚本輝",
      "Jockey": "潘頓",
      "Post": "6",
      "First Win Index": "14.0",
      "Race Day Win Index": "12.3",
      "lastWin": "11",
      "lastPosition": "10"
    },
    {
      "horseID": "HK_2022_H432",
      "Horse Number": "3",
      "Horse Name": "歡樂老撾",
      "Weight": "131",
      "Trainer": "桂福特",
      "Jockey": "艾兆禮",
      "Post": "11",
      "First Win Index": "11.4",
      "Race Day Win Index": "12.8",
      "lastWin": "11",
      "lastPosition": "07"
    },
    {
      "horseID": "HK_2024_K200",
      "Horse Number": "4",
      "Horse Name": "十力",
      "Weight": "131",
      "Trainer": "伍鵬志",
      "Jockey": "奧爾民",
      "Post": "3",
      "First Win Index": "74.2",
      "Race Day Win Index": "99",
      "lastWin": "18",
      "lastPosition": "08"
    },
    {
      "horseID": "HK_2021_G427",
      "Horse Number": "5",
      "Horse Name": "閃耀威龍",
      "Weight": "131",
      "Trainer": "文家良",
      "Jockey": "袁幸堯",
      "Post": "10",
      "First Win Index": "99",
      "Race Day Win Index": "18.0",
      "lastWin": "24",
      "lastPosition": "09"
    },
    {
      "horseID": "HK_2023_J338",
      "Horse Number": "6",
      "Horse Name": "幸運傳承",
      "Weight": "130",
      "Trainer": "方嘉柏",
      "Jockey": "莫雷拉",
      "Post": "12",
      "First Win Index": "14.0",
      "Race Day Win Index": "20.6",
      "lastWin": "6",
      "lastPosition": "07"
    },
    {
      "horseID": "HK_2023_J344",
      "Horse Number": "7",
      "Horse Name": "歷險大將",
      "Weight": "129",
      "Trainer": "徐雨石",
      "Jockey": "布浩榮",
      "Post": "9",
      "First Win Index": "99",
      "Race Day Win Index": "99",
      "lastWin": "14",
      "lastPosition": "08"
    },
    {
      "horseID": "HK_2022_H229",
      "Horse Number": "8",
      "Horse Name": "運來勇士",
      "Weight": "129",
      "Trainer": "葉楚航",
      "Jockey": "黃智弘",
      "Post": "5",
      "First Win Index": "99",
      "Race Day Win Index": "99",
      "lastWin": "56",
      "lastPosition": "12"
    },
    {
      "horseID": "HK_2022_H234",
      "Horse Number": "9",
      "Horse Name": "大利好運",
      "Weight": "128",
      "Trainer": "蔡約翰",
      "Jockey": "布文",
      "Post": "2",
      "First Win Index": "3.3",
      "Race Day Win Index": "3.1",
      "lastWin": "6.6",
      "lastPosition": "05"
    },
    {
      "horseID": "HK_2023_J002",
      "Horse Number": "10",
      "Horse Name": "一鹿歡騰",
      "Weight": "125",
      "Trainer": "告東尼",
      "Jockey": "鍾易禮",
      "Post": "1",
      "First Win Index": "99",
      "Race Day Win Index": "99",
      "lastWin": "14",
      "lastPosition": "13"
    },
    {
      "horseID": "HK_2022_H196",
      "Horse Number": "11",
      "Horse Name": "上市魅力",
      "Weight": "121",
      "Trainer": "蘇偉賢",
      "Jockey": "田泰安",
      "Post": "4",
      "First Win Index": "5.8",
      "Race Day Win Index": "6.7",
      "lastWin": "13",
      "lastPosition": "05"
    },
    {
      "horseID": "HK_2023_J271",
      "Horse Number": "12",
      "Horse Name": "幻影旋風",
      "Weight": "119",
      "Trainer": "丁冠豪",
      "Jockey": "巴度",
      "Post": "8",
      "First Win Index": "99",
      "Race Day Win Index": "49.5",
      "lastWin": "12",
      "lastPosition": "08"
    },
    {
      "horseID": "HK_2024_K028",
      "Horse Number": "13",
      "Horse Name": "東方魅影",
      "Weight": "118",
      "Trainer": "大衛希斯",
      "Jockey": "黃寶妮",
      "Post": "13",
      "First Win Index": "99",
      "Race Day Win Index": "99",
      "lastWin": "18",
      "lastPosition": "08"
    },
    {
      "horseID": "HK_2023_J453",
      "Horse Number": "14",
      "Horse Name": "樂矚心機",
      "Weight": "115",
      "Trainer": "鄭俊偉",
      "Jockey": "楊明綸",
      "Post": "14",
      "First Win Index": "99",
      "Race Day Win Index": "99",
      "lastWin": "51",
      "lastPosition": "11"
    }
  ]
}